{
  "id": "00000000-0000-0000-0000-000000000000",
  "prevId": "",
  "version": "7",
  "dialect": "postgresql",
  "tables": {
    "public._prisma_migrations": {
      "name": "_prisma_migrations",
      "schema": "",
      "columns": {
        "id": {
          "name": "id",
          "type": "varchar(36)",
          "primaryKey": true,
          "notNull": true
        },
        "checksum": {
          "name": "checksum",
          "type": "varchar(64)",
          "primaryKey": false,
          "notNull": true
        },
        "finished_at": {
          "name": "finished_at",
          "type": "timestamp with time zone",
          "primaryKey": false,
          "notNull": false
        },
        "migration_name": {
          "name": "migration_name",
          "type": "varchar(255)",
          "primaryKey": false,
          "notNull": true
        },
        "logs": {
          "name": "logs",
          "type": "text",
          "primaryKey": false,
          "notNull": false
        },
        "rolled_back_at": {
          "name": "rolled_back_at",
          "type": "timestamp with time zone",
          "primaryKey": false,
          "notNull": false
        },
        "started_at": {
          "name": "started_at",
          "type": "timestamp with time zone",
          "primaryKey": false,
          "notNull": true,
          "default": "now()"
        },
        "applied_steps_count": {
          "name": "applied_steps_count",
          "type": "integer",
          "primaryKey": false,
          "notNull": true,
          "default": 0
        }
      },
      "indexes": {},
      "foreignKeys": {},
      "compositePrimaryKeys": {},
      "uniqueConstraints": {},
      "checkConstraints": {},
      "policies": {},
      "isRLSEnabled": false
    },
    "public.VerificationToken": {
      "name": "VerificationToken",
      "schema": "",
      "columns": {
        "identifier": {
          "name": "identifier",
          "type": "text",
          "primaryKey": false,
          "notNull": true
        },
        "token": {
          "name": "token",
          "type": "text",
          "primaryKey": false,
          "notNull": true
        },
        "expires": {
          "name": "expires",
          "type": "timestamp(3)",
          "primaryKey": false,
          "notNull": true
        }
      },
      "indexes": {
        "VerificationToken_identifier_token_key": {
          "name": "VerificationToken_identifier_token_key",
          "columns": [
            {
              "expression": "identifier",
              "asc": true,
              "nulls": "last",
              "opclass": "text_ops",
              "isExpression": false
            },
            {
              "expression": "token",
              "asc": true,
              "nulls": "last",
              "opclass": "text_ops",
              "isExpression": false
            }
          ],
          "isUnique": true,
          "concurrently": false,
          "method": "btree",
          "with": {}
        },
        "VerificationToken_token_key": {
          "name": "VerificationToken_token_key",
          "columns": [
            {
              "expression": "token",
              "asc": true,
              "nulls": "last",
              "opclass": "text_ops",
              "isExpression": false
            }
          ],
          "isUnique": true,
          "concurrently": false,
          "method": "btree",
          "with": {}
        }
      },
      "foreignKeys": {},
      "compositePrimaryKeys": {},
      "uniqueConstraints": {},
      "checkConstraints": {},
      "policies": {},
      "isRLSEnabled": false
    },
    "public.Account": {
      "name": "Account",
      "schema": "",
      "columns": {
        "id": {
          "name": "id",
          "type": "text",
          "primaryKey": true,
          "notNull": true
        },
        "userId": {
          "name": "userId",
          "type": "text",
          "primaryKey": false,
          "notNull": true
        },
        "type": {
          "name": "type",
          "type": "text",
          "primaryKey": false,
          "notNull": true
        },
        "provider": {
          "name": "provider",
          "type": "text",
          "primaryKey": false,
          "notNull": true
        },
        "providerAccountId": {
          "name": "providerAccountId",
          "type": "text",
          "primaryKey": false,
          "notNull": true
        },
        "refresh_token": {
          "name": "refresh_token",
          "type": "text",
          "primaryKey": false,
          "notNull": false
        },
        "access_token": {
          "name": "access_token",
          "type": "text",
          "primaryKey": false,
          "notNull": false
        },
        "expires_at": {
          "name": "expires_at",
          "type": "integer",
          "primaryKey": false,
          "notNull": false
        },
        "token_type": {
          "name": "token_type",
          "type": "text",
          "primaryKey": false,
          "notNull": false
        },
        "scope": {
          "name": "scope",
          "type": "text",
          "primaryKey": false,
          "notNull": false
        },
        "id_token": {
          "name": "id_token",
          "type": "text",
          "primaryKey": false,
          "notNull": false
        },
        "session_state": {
          "name": "session_state",
          "type": "text",
          "primaryKey": false,
          "notNull": false
        }
      },
      "indexes": {
        "Account_provider_providerAccountId_key": {
          "name": "Account_provider_providerAccountId_key",
          "columns": [
            {
              "expression": "provider",
              "asc": true,
              "nulls": "last",
              "opclass": "text_ops",
              "isExpression": false
            },
            {
              "expression": "providerAccountId",
              "asc": true,
              "nulls": "last",
              "opclass": "text_ops",
              "isExpression": false
            }
          ],
          "isUnique": true,
          "concurrently": false,
          "method": "btree",
          "with": {}
        }
      },
      "foreignKeys": {
        "Account_userId_fkey": {
          "name": "Account_userId_fkey",
          "tableFrom": "Account",
          "tableTo": "User",
          "schemaTo": "public",
          "columnsFrom": [
            "userId"
          ],
          "columnsTo": [
            "id"
          ],
          "onDelete": "cascade",
          "onUpdate": "cascade"
        }
      },
      "compositePrimaryKeys": {},
      "uniqueConstraints": {},
      "checkConstraints": {},
      "policies": {},
      "isRLSEnabled": false
    },
    "public.Session": {
      "name": "Session",
      "schema": "",
      "columns": {
        "id": {
          "name": "id",
          "type": "text",
          "primaryKey": true,
          "notNull": true
        },
        "sessionToken": {
          "name": "sessionToken",
          "type": "text",
          "primaryKey": false,
          "notNull": true
        },
        "userId": {
          "name": "userId",
          "type": "text",
          "primaryKey": false,
          "notNull": true
        },
        "expires": {
          "name": "expires",
          "type": "timestamp(3)",
          "primaryKey": false,
          "notNull": true
        }
      },
      "indexes": {
        "Session_sessionToken_key": {
          "name": "Session_sessionToken_key",
          "columns": [
            {
              "expression": "sessionToken",
              "asc": true,
              "nulls": "last",
              "opclass": "text_ops",
              "isExpression": false
            }
          ],
          "isUnique": true,
          "concurrently": false,
          "method": "btree",
          "with": {}
        }
      },
      "foreignKeys": {
        "Session_userId_fkey": {
          "name": "Session_userId_fkey",
          "tableFrom": "Session",
          "tableTo": "User",
          "schemaTo": "public",
          "columnsFrom": [
            "userId"
          ],
          "columnsTo": [
            "id"
          ],
          "onDelete": "cascade",
          "onUpdate": "cascade"
        }
      },
      "compositePrimaryKeys": {},
      "uniqueConstraints": {},
      "checkConstraints": {},
      "policies": {},
      "isRLSEnabled": false
    },
    "public.Categories": {
      "name": "Categories",
      "schema": "",
      "columns": {
        "id": {
          "name": "id",
          "type": "text",
          "primaryKey": true,
          "notNull": true
        },
        "name": {
          "name": "name",
          "type": "text",
          "primaryKey": false,
          "notNull": true
        },
        "description": {
          "name": "description",
          "type": "text",
          "primaryKey": false,
          "notNull": true
        },
        "slug": {
          "name": "slug",
          "type": "text",
          "primaryKey": false,
          "notNull": true
        },
        "image": {
          "name": "image",
          "type": "text",
          "primaryKey": false,
          "notNull": true
        }
      },
      "indexes": {
        "Categories_slug_key": {
          "name": "Categories_slug_key",
          "columns": [
            {
              "expression": "slug",
              "asc": true,
              "nulls": "last",
              "opclass": "text_ops",
              "isExpression": false
            }
          ],
          "isUnique": true,
          "concurrently": false,
          "method": "btree",
          "with": {}
        }
      },
      "foreignKeys": {},
      "compositePrimaryKeys": {},
      "uniqueConstraints": {},
      "checkConstraints": {},
      "policies": {},
      "isRLSEnabled": false
    },
    "public.Courses": {
      "name": "Courses",
      "schema": "",
      "columns": {
        "id": {
          "name": "id",
          "type": "text",
          "primaryKey": true,
          "notNull": true
        },
        "name": {
          "name": "name",
          "type": "text",
          "primaryKey": false,
          "notNull": true
        },
        "description": {
          "name": "description",
          "type": "text",
          "primaryKey": false,
          "notNull": true
        },
        "slug": {
          "name": "slug",
          "type": "text",
          "primaryKey": false,
          "notNull": true
        },
        "image": {
          "name": "image",
          "type": "text",
          "primaryKey": false,
          "notNull": true
        },
        "level": {
          "name": "level",
          "type": "integer",
          "primaryKey": false,
          "notNull": true
        },
        "lessens": {
          "name": "lessens",
          "type": "integer",
          "primaryKey": false,
          "notNull": true
        },
        "createdAt": {
          "name": "createdAt",
          "type": "timestamp(3)",
          "primaryKey": false,
          "notNull": true,
          "default": "CURRENT_TIMESTAMP"
        },
        "updatedAt": {
          "name": "updatedAt",
          "type": "timestamp(3)",
          "primaryKey": false,
          "notNull": true
        },
        "categoryID": {
          "name": "categoryID",
          "type": "text",
          "primaryKey": false,
          "notNull": true
        }
      },
      "indexes": {
        "Courses_slug_key": {
          "name": "Courses_slug_key",
          "columns": [
            {
              "expression": "slug",
              "asc": true,
              "nulls": "last",
              "opclass": "text_ops",
              "isExpression": false
            }
          ],
          "isUnique": true,
          "concurrently": false,
          "method": "btree",
          "with": {}
        }
      },
      "foreignKeys": {
        "Courses_categoryID_fkey": {
          "name": "Courses_categoryID_fkey",
          "tableFrom": "Courses",
          "tableTo": "Categories",
          "schemaTo": "public",
          "columnsFrom": [
            "categoryID"
          ],
          "columnsTo": [
            "id"
          ],
          "onDelete": "restrict",
          "onUpdate": "cascade"
        }
      },
      "compositePrimaryKeys": {},
      "uniqueConstraints": {},
      "checkConstraints": {},
      "policies": {},
      "isRLSEnabled": false
    },
    "public.Lessons": {
      "name": "Lessons",
      "schema": "",
      "columns": {
        "id": {
          "name": "id",
          "type": "text",
          "primaryKey": true,
          "notNull": true
        },
        "name": {
          "name": "name",
          "type": "text",
          "primaryKey": false,
          "notNull": true
        },
        "description": {
          "name": "description",
          "type": "text",
          "primaryKey": false,
          "notNull": true
        },
        "slug": {
          "name": "slug",
          "type": "text",
          "primaryKey": false,
          "notNull": true
        },
        "unit": {
          "name": "unit",
          "type": "integer",
          "primaryKey": false,
          "notNull": true
        },
        "part": {
          "name": "part",
          "type": "integer",
          "primaryKey": false,
          "notNull": true
        },
        "duration": {
          "name": "duration",
          "type": "integer",
          "primaryKey": false,
          "notNull": true
        },
        "createdAt": {
          "name": "createdAt",
          "type": "timestamp(3)",
          "primaryKey": false,
          "notNull": true,
          "default": "CURRENT_TIMESTAMP"
        },
        "updatedAt": {
          "name": "updatedAt",
          "type": "timestamp(3)",
          "primaryKey": false,
          "notNull": true
        },
        "courseID": {
          "name": "courseID",
          "type": "text",
          "primaryKey": false,
          "notNull": true
        }
      },
      "indexes": {
        "Lessons_courseID_slug_key": {
          "name": "Lessons_courseID_slug_key",
          "columns": [
            {
              "expression": "courseID",
              "asc": true,
              "nulls": "last",
              "opclass": "text_ops",
              "isExpression": false
            },
            {
              "expression": "slug",
              "asc": true,
              "nulls": "last",
              "opclass": "text_ops",
              "isExpression": false
            }
          ],
          "isUnique": true,
          "concurrently": false,
          "method": "btree",
          "with": {}
        }
      },
      "foreignKeys": {
        "Lessons_courseID_fkey": {
          "name": "Lessons_courseID_fkey",
          "tableFrom": "Lessons",
          "tableTo": "Courses",
          "schemaTo": "public",
          "columnsFrom": [
            "courseID"
          ],
          "columnsTo": [
            "id"
          ],
          "onDelete": "restrict",
          "onUpdate": "cascade"
        }
      },
      "compositePrimaryKeys": {},
      "uniqueConstraints": {},
      "checkConstraints": {},
      "policies": {},
      "isRLSEnabled": false
    },
    "public.AdminUsers": {
      "name": "AdminUsers",
      "schema": "",
      "columns": {
        "id": {
          "name": "id",
          "type": "text",
          "primaryKey": true,
          "notNull": true
        },
        "role": {
          "name": "role",
          "type": "Role",
          "typeSchema": "public",
          "primaryKey": false,
          "notNull": true
        },
        "createdAt": {
          "name": "createdAt",
          "type": "timestamp(3)",
          "primaryKey": false,
          "notNull": true,
          "default": "CURRENT_TIMESTAMP"
        },
        "updatedAt": {
          "name": "updatedAt",
          "type": "timestamp(3)",
          "primaryKey": false,
          "notNull": true
        },
        "userId": {
          "name": "userId",
          "type": "text",
          "primaryKey": false,
          "notNull": true
        }
      },
      "indexes": {
        "AdminUsers_userId_key": {
          "name": "AdminUsers_userId_key",
          "columns": [
            {
              "expression": "userId",
              "asc": true,
              "nulls": "last",
              "opclass": "text_ops",
              "isExpression": false
            }
          ],
          "isUnique": true,
          "concurrently": false,
          "method": "btree",
          "with": {}
        }
      },
      "foreignKeys": {
        "AdminUsers_userId_fkey": {
          "name": "AdminUsers_userId_fkey",
          "tableFrom": "AdminUsers",
          "tableTo": "User",
          "schemaTo": "public",
          "columnsFrom": [
            "userId"
          ],
          "columnsTo": [
            "id"
          ],
          "onDelete": "cascade",
          "onUpdate": "cascade"
        }
      },
      "compositePrimaryKeys": {},
      "uniqueConstraints": {},
      "checkConstraints": {},
      "policies": {},
      "isRLSEnabled": false
    },
    "public.User": {
      "name": "User",
      "schema": "",
      "columns": {
        "id": {
          "name": "id",
          "type": "text",
          "primaryKey": true,
          "notNull": true
        },
        "name": {
          "name": "name",
          "type": "text",
          "primaryKey": false,
          "notNull": true
        },
        "email": {
          "name": "email",
          "type": "text",
          "primaryKey": false,
          "notNull": true
        },
        "emailVerified": {
          "name": "emailVerified",
          "type": "timestamp(3)",
          "primaryKey": false,
          "notNull": false
        },
        "image": {
          "name": "image",
          "type": "text",
          "primaryKey": false,
          "notNull": false
        },
        "timezone": {
          "name": "timezone",
          "type": "text",
          "primaryKey": false,
          "notNull": true,
          "default": "'America/Los_Angeles'"
        },
        "league": {
          "name": "league",
          "type": "text",
          "primaryKey": false,
          "notNull": true,
          "default": "'bronze'"
        },
        "points": {
          "name": "points",
          "type": "integer",
          "primaryKey": false,
          "notNull": true,
          "default": 10
        },
        "streak": {
          "name": "streak",
          "type": "integer",
          "primaryKey": false,
          "notNull": true,
          "default": 0
        },
        "learningGoal": {
          "name": "learningGoal",
          "type": "integer",
          "primaryKey": false,
          "notNull": true,
          "default": 1
        },
        "username": {
          "name": "username",
          "type": "text",
          "primaryKey": false,
          "notNull": true
        }
      },
      "indexes": {
        "User_email_key": {
          "name": "User_email_key",
          "columns": [
            {
              "expression": "email",
              "asc": true,
              "nulls": "last",
              "opclass": "text_ops",
              "isExpression": false
            }
          ],
          "isUnique": true,
          "concurrently": false,
          "method": "btree",
          "with": {}
        },
        "User_username_key": {
          "name": "User_username_key",
          "columns": [
            {
              "expression": "username",
              "asc": true,
              "nulls": "last",
              "opclass": "text_ops",
              "isExpression": false
            }
          ],
          "isUnique": true,
          "concurrently": false,
          "method": "btree",
          "with": {}
        }
      },
      "foreignKeys": {},
      "compositePrimaryKeys": {},
      "uniqueConstraints": {},
      "checkConstraints": {},
      "policies": {},
      "isRLSEnabled": false
    },
    "public.CourseProgress": {
      "name": "CourseProgress",
      "schema": "",
      "columns": {
        "id": {
          "name": "id",
          "type": "text",
          "primaryKey": true,
          "notNull": true
        },
        "userID": {
          "name": "userID",
          "type": "text",
          "primaryKey": false,
          "notNull": true
        },
        "courseID": {
          "name": "courseID",
          "type": "text",
          "primaryKey": false,
          "notNull": true
        },
        "percentage": {
          "name": "percentage",
          "type": "integer",
          "primaryKey": false,
          "notNull": true
        },
        "resumeURL": {
          "name": "resumeURL",
          "type": "text",
          "primaryKey": false,
          "notNull": true
        },
        "createdAt": {
          "name": "createdAt",
          "type": "timestamp(3)",
          "primaryKey": false,
          "notNull": true,
          "default": "CURRENT_TIMESTAMP"
        },
        "updatedAt": {
          "name": "updatedAt",
          "type": "timestamp(3)",
          "primaryKey": false,
          "notNull": true
        }
      },
      "indexes": {
        "CourseProgress_userID_courseID_key": {
          "name": "CourseProgress_userID_courseID_key",
          "columns": [
            {
              "expression": "userID",
              "asc": true,
              "nulls": "last",
              "opclass": "text_ops",
              "isExpression": false
            },
            {
              "expression": "courseID",
              "asc": true,
              "nulls": "last",
              "opclass": "text_ops",
              "isExpression": false
            }
          ],
          "isUnique": true,
          "concurrently": false,
          "method": "btree",
          "with": {}
        }
      },
      "foreignKeys": {
        "CourseProgress_userID_fkey": {
          "name": "CourseProgress_userID_fkey",
          "tableFrom": "CourseProgress",
          "tableTo": "User",
          "schemaTo": "public",
          "columnsFrom": [
            "userID"
          ],
          "columnsTo": [
            "id"
          ],
          "onDelete": "cascade",
          "onUpdate": "cascade"
        },
        "CourseProgress_courseID_fkey": {
          "name": "CourseProgress_courseID_fkey",
          "tableFrom": "CourseProgress",
          "tableTo": "Courses",
          "schemaTo": "public",
          "columnsFrom": [
            "courseID"
          ],
          "columnsTo": [
            "id"
          ],
          "onDelete": "cascade",
          "onUpdate": "cascade"
        }
      },
      "compositePrimaryKeys": {},
      "uniqueConstraints": {},
      "checkConstraints": {},
      "policies": {},
      "isRLSEnabled": false
    },
    "public.LessonProgress": {
      "name": "LessonProgress",
      "schema": "",
      "columns": {
        "id": {
          "name": "id",
          "type": "text",
          "primaryKey": true,
          "notNull": true
        },
        "userID": {
          "name": "userID",
          "type": "text",
          "primaryKey": false,
          "notNull": true
        },
        "lessonID": {
          "name": "lessonID",
          "type": "text",
          "primaryKey": false,
          "notNull": true
        },
        "progress": {
          "name": "progress",
          "type": "text",
          "primaryKey": false,
          "notNull": true
        },
        "resumeURL": {
          "name": "resumeURL",
          "type": "text",
          "primaryKey": false,
          "notNull": true
        },
        "progressMap": {
          "name": "progressMap",
          "type": "text",
          "primaryKey": false,
          "notNull": true
        },
        "createdAt": {
          "name": "createdAt",
          "type": "timestamp(3)",
          "primaryKey": false,
          "notNull": true,
          "default": "CURRENT_TIMESTAMP"
        },
        "updatedAt": {
          "name": "updatedAt",
          "type": "timestamp(3)",
          "primaryKey": false,
          "notNull": true
        }
      },
      "indexes": {
        "LessonProgress_userID_lessonID_key": {
          "name": "LessonProgress_userID_lessonID_key",
          "columns": [
            {
              "expression": "userID",
              "asc": true,
              "nulls": "last",
              "opclass": "text_ops",
              "isExpression": false
            },
            {
              "expression": "lessonID",
              "asc": true,
              "nulls": "last",
              "opclass": "text_ops",
              "isExpression": false
            }
          ],
          "isUnique": true,
          "concurrently": false,
          "method": "btree",
          "with": {}
        }
      },
      "foreignKeys": {
        "LessonProgress_userID_fkey": {
          "name": "LessonProgress_userID_fkey",
          "tableFrom": "LessonProgress",
          "tableTo": "User",
          "schemaTo": "public",
          "columnsFrom": [
            "userID"
          ],
          "columnsTo": [
            "id"
          ],
          "onDelete": "cascade",
          "onUpdate": "cascade"
        },
        "LessonProgress_lessonID_fkey": {
          "name": "LessonProgress_lessonID_fkey",
          "tableFrom": "LessonProgress",
          "tableTo": "Lessons",
          "schemaTo": "public",
          "columnsFrom": [
            "lessonID"
          ],
          "columnsTo": [
            "id"
          ],
          "onDelete": "cascade",
          "onUpdate": "cascade"
        }
      },
      "compositePrimaryKeys": {},
      "uniqueConstraints": {},
      "checkConstraints": {},
      "policies": {},
      "isRLSEnabled": false
    }
  },
  "enums": {
    "public.Role": {
      "name": "Role",
      "values": [
        "admin",
        "editor"
      ],
      "schema": "public"
    }
  },
  "schemas": {},
  "sequences": {},
  "roles": {},
  "policies": {},
  "views": {},
  "_meta": {
    "schemas": {},
    "tables": {},
    "columns": {}
  },
  "internal": {
    "tables": {}
  }
}